ocean_sparkconnect/__init__.py
ocean_sparkconnect/inverse_websockify.py
ocean_sparkconnect/ocean_spark_session.py
ocean_sparkconnect/py.typed
ocean_sparkconnect-0.3.6.dist-info/METADATA
ocean_sparkconnect-0.3.6.dist-info/WHEEL
ocean_sparkconnect-0.3.6.dist-info/RECORD
