Metadata-Version: 2.1
Name: ocean-sparkconnect
Version: 0.3.6
Summary: Spark Connect adapter for Ocean Spark
Author: Sigmar Stefansson
Author-email: sigmar@netapp.com
Requires-Python: >=3.9,<4.0
Classifier: Programming Language :: Python :: 3
Classifier: Programming Language :: Python :: 3.9
Classifier: Programming Language :: Python :: 3.10
Classifier: Programming Language :: Python :: 3.11
Classifier: Programming Language :: Python :: 3.12
Requires-Dist: googleapis-common-protos (>=1.60.0,<2.0.0)
Requires-Dist: grpcio (>=1.57.0,<2.0.0)
Requires-Dist: grpcio-status (>=1.57.0,<2.0.0)
Requires-Dist: pandas (>=2.0.3,<3.0.0)
Requires-Dist: pyarrow
Requires-Dist: pyspark (>=3.4.0,<4.0.0)
Requires-Dist: websockets (>=11.0.3,<12.0.0)
